<?xml version="1.0" encoding="UTF-8"?>
<dataSchema>
	<description>
		<name>A300</name>
		<comments>Selected from old MDO project 19/20</comments>
	</description>
	<constants>
		<E_al>70000000000</E_al>
		<sig_yield_tens>295000000</sig_yield_tens>
		<sig_yield_comp>295000000</sig_yield_comp>
		<rho_al>2800</rho_al>
		<n_max>2.5</n_max>
		<n_cruise>1</n_cruise>
		<rib_pitch>0.5</rib_pitch>
		<eta_panel>0.96</eta_panel>
		<rho_fuel>817.15</rho_fuel>
		<f_tank>0.93</f_tank>
		<h_cruise>10668</h_cruise>
		<T_cruise>208.8</T_cruise>
		<rho_cruise>0.3796</rho_cruise>
		<visc_kin_cruise>3.8052e-05</visc_kin_cruise>
		<c_sound>289.6478</c_sound>
		<C_D_aw_area>256.3956</C_D_aw_area>
		<C_D_aw>0.012372</C_D_aw>
	</constants>
	<wing>
		<inner>
			<foil>
				<b_1>0.2337438</b_1>
				<b_2>0.08835458999999998</b_2>
				<b_3>0.2342162</b_3>
				<b_4>0.06663904</b_4>
				<b_5>0.17819580000000002</b_5>
				<b_6>0.2989059</b_6>
				<b_7>-0.2131605</b_7>
				<b_8>-0.1521207</b_8>
				<b_9>-0.053337630000000004</b_9>
				<b_10>-0.3148052</b_10>
				<b_11>0.0666468</b_11>
				<b_12>0.36008249999999997</b_12>
			</foil>
			<sweep>16.9785</sweep>
			<twist>0</twist>
			<chord>7.614000000000001</chord>
			<dihedral>0</dihedral>
			<span>9.06</span>
		</inner>
		<outer>
			<foil>
				<b_1>0.1418141</b_1>
				<b_2>0.044429819999999995</b_2>
				<b_3>0.19187559999999998</b_3>
				<b_4>0.04308552</b_4>
				<b_5>0.159201</b_5>
				<b_6>0.2357876</b_6>
				<b_7>-0.1042118</b_7>
				<b_8>-0.12700566</b_8>
				<b_9>-0.02781641</b_9>
				<b_10>-0.3652139</b_10>
				<b_11>0.05711316999999999</b_11>
				<b_12>0.204855</b_12>
			</foil>
			<sweep>26.535</sweep>
			<twist>0</twist>
			<chord>2.1725</chord>
			<dihedral>0</dihedral>
			<span>14.562399999999998</span>
		</outer>
		<chord>9.1166</chord>
		<chord>8.5497</chord>
		<chord>7.9828</chord>
		<chord>7.4159</chord>
		<chord>6.849</chord>
		<chord>6.2822</chord>
		<chord>5.7957</chord>
		<chord>5.3896</chord>
		<chord>4.9835</chord>
		<chord>4.5774</chord>
		<chord>4.1713</chord>
		<chord>3.7652</chord>
		<chord>3.3591</chord>
		<chord>2.953</chord>
		<cl>1.1679</cl>
		<cl>1.2336</cl>
		<cl>1.2936</cl>
		<cl>1.3492</cl>
		<cl>1.3999</cl>
		<cl>1.4441</cl>
		<cl>1.4772</cl>
		<cl>1.5224</cl>
		<cl>1.5657</cl>
		<cl>1.6023</cl>
		<cl>1.6256</cl>
		<cl>1.621</cl>
		<cl>1.5486</cl>
		<cl>1.2817</cl>
		<cdi>0.1379</cdi>
		<cdi>0.1246</cdi>
		<cdi>0.1171</cdi>
		<cdi>0.1101</cdi>
		<cdi>0.1034</cdi>
		<cdi>0.0986</cdi>
		<cdi>0.0766</cdi>
		<cdi>0.0613</cdi>
		<cdi>0.0466</cdi>
		<cdi>0.0318</cdi>
		<cdi>0.0171</cdi>
		<cdi>0.0024</cdi>
		<cdi>-0.0123</cdi>
		<cdi>-0.0238</cdi>
		<ccl>11.8909</ccl>
		<ccl>11.6867</ccl>
		<ccl>11.3222</ccl>
		<ccl>10.8145</ccl>
		<ccl>10.1724</ccl>
		<ccl>9.5562</ccl>
		<ccl>9.157</ccl>
		<ccl>8.7286</ccl>
		<ccl>8.2517</ccl>
		<ccl>7.7161</ccl>
		<ccl>7.1055</ccl>
		<ccl>6.3815</ccl>
		<ccl>5.4427</ccl>
		<ccl>3.9732</ccl>
		<cm_c4>-0.294</cm_c4>
		<cm_c4>-0.2838</cm_c4>
		<cm_c4>-0.2751</cm_c4>
		<cm_c4>-0.2686</cm_c4>
		<cm_c4>-0.2667</cm_c4>
		<cm_c4>-0.2529</cm_c4>
		<cm_c4>-0.2343</cm_c4>
		<cm_c4>-0.2218</cm_c4>
		<cm_c4>-0.2117</cm_c4>
		<cm_c4>-0.2018</cm_c4>
		<cm_c4>-0.1896</cm_c4>
		<cm_c4>-0.1714</cm_c4>
		<cm_c4>-0.1389</cm_c4>
		<cm_c4>-0.079</cm_c4>
		<C_L>0.67817</C_L>
		<area>217.9843</area>
		<Yst>0.906</Yst>
		<Yst>2.718</Yst>
		<Yst>4.53</Yst>
		<Yst>6.342</Yst>
		<Yst>8.154</Yst>
		<Yst>9.869</Yst>
		<Yst>11.4871</Yst>
		<Yst>13.1051</Yst>
		<Yst>14.7232</Yst>
		<Yst>16.3412</Yst>
		<Yst>17.9592</Yst>
		<Yst>19.5773</Yst>
		<Yst>21.1953</Yst>
		<Yst>22.8134</Yst>
		<C_D>0.032623</C_D>
	</wing>
	<weights>
		<a_w>846654.2756</a_w>
		<des>0</des>
		<str_wing>328063.077</str_wing>
		<to_max>1906983.7893</to_max>
		<fuel>732266.4367</fuel>
	</weights>
	<performance>
		<range>0</range>
		<V_cruise>231.48</V_cruise>
		<V_max>246.912</V_max>
		<C_T>0.00018639</C_T>
		<range_cruise>7408000</range_cruise>
	</performance>
	<constraints>
		<constants>
			<initial_load_factor>0</initial_load_factor>
			<initial_load>6523.5324</initial_load>
		</constants>
		<fuel>36.1191</fuel>
		<load>2224.7297</load>
	</constraints>
	<architectureNodes>
		<couplingCopyVariables>
			<dataSchemaCopy>
				<weights>
					<str_wing>433615.734</str_wing>
					<fuel>772457.3544</fuel>
				</weights>
			</dataSchemaCopy>
		</couplingCopyVariables>
	</architectureNodes>
</dataSchema>